{
    "modifies": [
		"enderscape:mirestone_ruins/chest",
		"hopo:chests/mineshaft/base/amethyst",
		"hopo:chests/mineshaft/base/archer",
		"hopo:chests/mineshaft/base/armor",
		"hopo:chests/mineshaft/base/bedroom",
		"hopo:chests/mineshaft/base/books",
		"hopo:chests/mineshaft/base/brown_mushroom",
		"hopo:chests/mineshaft/base/copper",
		"hopo:chests/mineshaft/base/crafting",
		"hopo:chests/mineshaft/base/diamond",
		"hopo:chests/mineshaft/base/emerald",
		"hopo:chests/mineshaft/base/food",
		"hopo:chests/mineshaft/base/fossils",
		"hopo:chests/mineshaft/base/gold",
		"hopo:chests/mineshaft/base/iron",
		"hopo:chests/mineshaft/base/lapis",
		"hopo:chests/mineshaft/base/potions",
		"hopo:chests/mineshaft/base/prison",
		"hopo:chests/mineshaft/base/red_mushroom",
		"hopo:chests/mineshaft/base/redstone",
		"hopo:chests/mineshaft/base/rip",
		"hopo:chests/mineshaft/base/smelting",
		"hopo:chests/mineshaft/base/tnt",
		"hopo:chests/mineshaft/base/tools",
		"hopo:chests/mineshaft/base/weapons",
		"hopo:chests/mineshaft/big_rooms/archer",
		"hopo:chests/mineshaft/big_rooms/copper",
		"hopo:chests/mineshaft/big_rooms/farm_beetroot",
		"hopo:chests/mineshaft/big_rooms/farm_carrot",
		"hopo:chests/mineshaft/big_rooms/farm_melon",
		"hopo:chests/mineshaft/big_rooms/farm_potato",
		"hopo:chests/mineshaft/big_rooms/farm_pumpkin",
		"hopo:chests/mineshaft/big_rooms/farm_wheat",
		"hopo:chests/mineshaft/big_rooms/iron_golem",
		"hopo:chests/mineshaft/big_rooms/map",
		"hopo:chests/mineshaft/big_rooms/music",
		"hopo:chests/mineshaft/big_rooms/potion",
		"hopo:chests/mineshaft/big_rooms/prison",
		"hopo:chests/mineshaft/big_rooms/stews",
		"hopo:chests/portal/dripstone_portal",
		"legendarymonuments:chests/dragoeleki_chest",
		"legendarymonuments:chests/lugia_temple_chest",
		"legendarymonuments:chests/regirock_chest",
		"minecraft:chests/bastion_treasure",
		"minecraft:chests/illager_mansion/ancient_city_raid_chest",
		"minecraft:chests/illager_mansion/ravager_chest",
		"minecraft:chests/shipwreck_treasure",
		"strongholds:stronghold_treasure",
		"minecraft:chests/trial_chambers/reward_ominous",
		"minecraft:chests/trial_chambers/reward_ominous_rare",
		"minecraft:chests/trial_chambers/reward_ominous_unique",
		"mns:chests/uncommon",
		"nova_structures:chests/conduit_ruin/conduit_ruin_big",
		"nova_structures:chests/dungeon_1",
		"nova_structures:chests/dungeon_2",
		"nova_structures:chests/dungeon_3",
		"nova_structures:chests/dungeon_4",
		"nova_structures:chests/dungeon_5",
		"nova_structures:chests/dungeon_6",
		"nova_structures:chests/dungeon_7",
		"nova_structures:chests/end_castle/castle_bar",
		"nova_structures:chests/end_castle/greater_loot",
		"nova_structures:chests/hamlet/hamlet_tresure",
		"nova_structures:chests/mangrove_witchhud",
		"nova_structures:chests/nether_keep/vault_keep",
		"nova_structures:chests/nether_skeleton_tower/skeleton_tower_camp",
		"nova_structures:chests/nether_skeleton_tower/skeleton_tower_supply",
		"nova_structures:chests/piglin_outstation/outstation_treasure",
		"nova_structures:chests/shrine/combat_treasure_3",
		"nova_structures:chests/shrine/combat_treasure_4",
		"nova_structures:chests/shrine/combat_treasure_5"
    ],
    "pools": [
        {
            "rolls": 1,
            "bonus_rolls": 0,
            "entries": [
                {
                    "type": "minecraft:loot_table",
                    "value": "jecobblemon:chests/t7"
                }
            ]
        }
    ]
}